dino/__init__.py
dino/core.py
dino/dino.py
dino/agents/__init__.py
dino/agents/agent.py
dino/agents/random.py
dino/agents/learners/__init__.py
dino/agents/learners/learner.py
dino/agents/tools/__init__.py
dino/agents/tools/datasets/__init__.py
dino/agents/tools/datasets/dataset.py
dino/agents/tools/datasets/model_dataset.py
dino/agents/tools/models/__init__.py
dino/agents/tools/models/model.py
dino/agents/tools/models/regression.py
dino/agents/tools/performers/__init__.py
dino/agents/tools/performers/performer.py
dino/agents/tools/planners/__init__.py
dino/agents/tools/planners/planner.py
dino/agents/tools/planners/rrtplanner.py
dino/agents/tools/policies/__init__.py
dino/agents/tools/policies/policy.py
dino/agents/tools/strategies/__init__.py
dino/agents/tools/strategies/autonomous.py
dino/agents/tools/strategies/random.py
dino/agents/tools/strategies/strategy.py
dino/agents/tools/strategies/strategy_set.py
dino/data/__init__.py
dino/data/abstract.py
dino/data/contextarea.py
dino/data/data.py
dino/data/dataspace.py
dino/data/event.py
dino/data/multispace.py
dino/data/operations.cp38-win_amd64.pyd
dino/data/path.py
dino/data/region.py
dino/data/space.py
dino/data/spacemanager.py
dino/environments/__init__.py
dino/environments/environment.py
dino/environments/scene.py
dino/environments/engines/__init__.py
dino/environments/engines/engine.py
dino/environments/engines/tools/__init__.py
dino/environments/engines/tools/panda.py
dino/environments/playground/__init__.py
dino/environments/playground/agent.py
dino/environments/playground/button.py
dino/environments/playground/cylinder.py
dino/environments/playground/environment.py
dino/environments/playground/scenes.py
dino/environments/playground/wall.py
dino/environments/priors/__init__.py
dino/environments/priors/maps/__init__.py
dino/environments/priors/maps/auto.py
dino/environments/priors/maps/playground.py
dino/environments/priors/maps/pymunk.py
dino/evaluation/__init__.py
dino/evaluation/evaluator.py
dinos-0.1.1.dist-info/LICENSE.md
dinos-0.1.1.dist-info/METADATA
dinos-0.1.1.dist-info/WHEEL
dinos-0.1.1.dist-info/top_level.txt
dinos-0.1.1.dist-info/RECORD
