Metadata-Version: 2.1
Name: dinos
Version: 0.1.1
Summary: Active Learning Environments
Home-page: https://github.com/Pikalchemist/dinos
Author: Alexandre Manoury
Author-email: alex@pika.tf
License: UNKNOWN
Platform: UNKNOWN
Classifier: Programming Language :: Python :: 3
Classifier: License :: OSI Approved :: MIT License
Classifier: Operating System :: OS Independent
Requires-Dist: exlab
Requires-Dist: Cython
Requires-Dist: matplotlib
Requires-Dist: numpy
Requires-Dist: panda3d
Requires-Dist: Pillow
Requires-Dist: pygame
Requires-Dist: pymunk
Requires-Dist: scikit-learn
Requires-Dist: scipy
Requires-Dist: sklearn
